kwikapi/django/__init__.py
kwikapi/django/kwikapi_django.py
kwikapi_django-0.2.8.dist-info/LICENSE
kwikapi_django-0.2.8.dist-info/METADATA
kwikapi_django-0.2.8.dist-info/WHEEL
kwikapi_django-0.2.8.dist-info/top_level.txt
kwikapi_django-0.2.8.dist-info/RECORD
